h_transformer_1d/__init__.py
h_transformer_1d/autoregressive_wrapper.py
h_transformer_1d/h_transformer_1d.py
h_transformer_1d/reversible.py
h_transformer_1d-0.1.9.dist-info/LICENSE
h_transformer_1d-0.1.9.dist-info/METADATA
h_transformer_1d-0.1.9.dist-info/WHEEL
h_transformer_1d-0.1.9.dist-info/top_level.txt
h_transformer_1d-0.1.9.dist-info/RECORD
