Metadata-Version: 2.1
Name: h-transformer-1d
Version: 0.1.9
Summary: H-Transformer 1D - Pytorch
Home-page: https://github.com/lucidrains/h-transformer-1d
Author: Phil Wang
Author-email: lucidrains@gmail.com
License: MIT
Keywords: artificial intelligence,deep learning,transformers,efficient attention
Classifier: Development Status :: 4 - Beta
Classifier: Intended Audience :: Developers
Classifier: Topic :: Scientific/Engineering :: Artificial Intelligence
Classifier: License :: OSI Approved :: MIT License
Classifier: Programming Language :: Python :: 3.6
License-File: LICENSE
Requires-Dist: einops >=0.3
Requires-Dist: rotary-embedding-torch >=0.5.3
Requires-Dist: torch >=1.6
